common_utils/__init__.py
common_utils/error_extensions.py
common_utils/helpers.py
pylearn_flask_api_utils-0.1.1.dist-info/METADATA
pylearn_flask_api_utils-0.1.1.dist-info/WHEEL
pylearn_flask_api_utils-0.1.1.dist-info/top_level.txt
pylearn_flask_api_utils-0.1.1.dist-info/RECORD
